[
  {
    "items": [
      {
        "id": "m4",
        "name": "Spaghetti Carbonara",
        "price": "10.99",
        "description": "Al dente spaghetti with a creamy sauce made from egg yolk, pecorino cheese, pancetta, and pepper.",
        "image": "images/spaghetti-carbonara.jpg",
        "quantity": 3
      },
      {
        "id": "m3",
        "name": "Caesar Salad",
        "price": "7.99",
        "description": "Romaine lettuce tossed in Caesar dressing, topped with croutons and parmesan shavings.",
        "image": "images/caesar-salad.jpg",
        "quantity": 1
      }
    ],
    "customer": {
      "name": "Dora Babu Kondala",
      "email": "test1@gmail.com",
      "street": "pragathi nagar",
      "postal-code": "500037",
      "city": "Hyderabad"
    },
    "id": "554.573479255966"
  },
  {
    "items": [
      {
        "id": "m4",
        "name": "Spaghetti Carbonara",
        "price": "10.99",
        "description": "Al dente spaghetti with a creamy sauce made from egg yolk, pecorino cheese, pancetta, and pepper.",
        "image": "images/spaghetti-carbonara.jpg",
        "quantity": 3
      },
      {
        "id": "m3",
        "name": "Caesar Salad",
        "price": "7.99",
        "description": "Romaine lettuce tossed in Caesar dressing, topped with croutons and parmesan shavings.",
        "image": "images/caesar-salad.jpg",
        "quantity": 1
      }
    ],
    "customer": {
      "name": "Dora Babu Kondala",
      "email": "test1@gmail.com",
      "street": "pragathi nagar",
      "postal-code": "500037",
      "city": "Hyderabad"
    },
    "id": "767.8814922597659"
  }
]
